helloworld.py
solcapta-0.0.1.dist-info/METADATA
solcapta-0.0.1.dist-info/WHEEL
solcapta-0.0.1.dist-info/top_level.txt
solcapta-0.0.1.dist-info/RECORD
