Metadata-Version: 2.1
Name: solcapta
Version: 0.0.1
Summary: first pip package
Home-page: UNKNOWN
Author: UNKNOWN
Author-email: UNKNOWN
License: UNKNOWN
Platform: UNKNOWN
